{
  "legislative_session": "114",
  "identifier": "HB 1237",
  "title": "Boards and Commissions - As enacted, prohibits the exclusion of persons from membership on state regulatory and health-related boards on the basis of race, color, ethnicity, and national origin; prohibits such boards from establishing or operating under race-based policies pertaining to their composition; removes requirement that appointing authorities strive to ensure certain boards and commissions are represented by members of racial minorities. - Amends TCA Title 4, Chapter 21; Title 9; Title 62; Title 63 and Title 68.",
  "from_organization": "~{\"classification\": \"lower\"}",
  "classification": [
    "bill"
  ],
  "subject": [
    "Boards and Commissions"
  ],
  "abstracts": [],
  "other_titles": [],
  "other_identifiers": [
    {
      "identifier": "SB 1235"
    }
  ],
  "actions": [
    {
      "description": "Filed for introduction",
      "date": "2025-02-06",
      "organization_id": "~{\"classification\": \"lower\"}",
      "classification": [
        "filing"
      ],
      "related_entities": [],
      "_processing": {
        "log_file_created": "2025-10-25T03:23:16Z"
      }
    },
    {
      "description": "Intro., P1C.",
      "date": "2025-02-10",
      "organization_id": "~{\"classification\": \"lower\"}",
      "classification": [
        "introduction"
      ],
      "related_entities": [],
      "_processing": {
        "log_file_created": "2025-10-25T03:23:16Z"
      }
    },
    {
      "description": "Assigned to s/c Departments & Agencies Subcommittee",
      "date": "2025-02-12",
      "organization_id": "~{\"classification\": \"lower\"}",
      "classification": [
        "referral-committee"
      ],
      "related_entities": [],
      "_processing": {
        "log_file_created": "2025-10-25T03:23:16Z"
      }
    },
    {
      "description": "P2C, ref. to State & Local Government Committee",
      "date": "2025-02-12",
      "organization_id": "~{\"classification\": \"lower\"}",
      "classification": [
        "referral-committee"
      ],
      "related_entities": [],
      "_processing": {
        "log_file_created": "2025-10-25T03:23:16Z"
      }
    },
    {
      "description": "Placed on s/c cal Departments & Agencies Subcommittee for 2/25/2025",
      "date": "2025-02-19",
      "organization_id": "~{\"classification\": \"lower\"}",
      "classification": [],
      "related_entities": [],
      "_processing": {
        "log_file_created": "2025-10-25T03:23:16Z"
      }
    },
    {
      "description": "Rec. for pass by s/c ref. to  State & Local Government Committee",
      "date": "2025-02-25",
      "organization_id": "~{\"classification\": \"lower\"}",
      "classification": [
        "committee-passage-favorable"
      ],
      "related_entities": [],
      "_processing": {
        "log_file_created": "2025-10-25T03:23:16Z"
      }
    },
    {
      "description": "Placed on cal. State & Local Government Committee for 3/5/2025",
      "date": "2025-02-26",
      "organization_id": "~{\"classification\": \"lower\"}",
      "classification": [],
      "related_entities": [],
      "_processing": {
        "log_file_created": "2025-10-25T03:23:16Z"
      }
    },
    {
      "description": "Placed on cal. Calendar & Rules Committee for 3/6/2025",
      "date": "2025-03-05",
      "organization_id": "~{\"classification\": \"lower\"}",
      "classification": [],
      "related_entities": [],
      "_processing": {
        "log_file_created": "2025-10-25T03:23:16Z"
      }
    },
    {
      "description": "Rec. for pass. if am., ref. to  Calendar & Rules Committee",
      "date": "2025-03-05",
      "organization_id": "~{\"classification\": \"lower\"}",
      "classification": [
        "committee-passage-favorable"
      ],
      "related_entities": [],
      "_processing": {
        "log_file_created": "2025-10-25T03:23:16Z"
      }
    },
    {
      "description": "H. Placed on Regular Calendar for 3/10/2025",
      "date": "2025-03-06",
      "organization_id": "~{\"classification\": \"lower\"}",
      "classification": [],
      "related_entities": [],
      "_processing": {
        "log_file_created": "2025-10-25T03:23:16Z"
      }
    },
    {
      "description": "Passed H., as am., Ayes 71, Nays 23, PNV 0",
      "date": "2025-03-10",
      "organization_id": "~{\"classification\": \"lower\"}",
      "classification": [
        "passage"
      ],
      "related_entities": [],
      "_processing": {
        "log_file_created": "2025-10-25T03:23:16Z"
      }
    },
    {
      "description": "Sponsor(s) Added.",
      "date": "2025-03-10",
      "organization_id": "~{\"classification\": \"lower\"}",
      "classification": [
        "sponsorship"
      ],
      "related_entities": [],
      "_processing": {
        "log_file_created": "2025-10-25T03:23:16Z"
      }
    },
    {
      "description": "H. adopted am. (Amendment 1 - HA0053)",
      "date": "2025-03-10",
      "organization_id": "~{\"classification\": \"lower\"}",
      "classification": [
        "amendment-passage"
      ],
      "related_entities": [],
      "_processing": {
        "log_file_created": "2025-10-25T03:23:16Z"
      }
    },
    {
      "description": "Engrossed; ready for transmission to Sen.",
      "date": "2025-03-11",
      "organization_id": "~{\"classification\": \"lower\"}",
      "classification": [
        "receipt"
      ],
      "related_entities": [],
      "_processing": {
        "log_file_created": "2025-10-25T03:23:16Z"
      }
    },
    {
      "description": "Received from House, Passed on First Consideration",
      "date": "2025-03-13",
      "organization_id": "~{\"classification\": \"lower\"}",
      "classification": [
        "introduction"
      ],
      "related_entities": [],
      "_processing": {
        "log_file_created": "2025-10-25T03:23:16Z"
      }
    },
    {
      "description": "Passed Senate as amended, Ayes 24, Nays 6",
      "date": "2025-03-31",
      "organization_id": "~{\"classification\": \"upper\"}",
      "classification": [
        "passage"
      ],
      "related_entities": [],
      "_processing": {
        "log_file_created": "2025-10-25T03:23:16Z"
      }
    },
    {
      "description": "Senate adopted Amendment (Amendment 1 - SA0137)",
      "date": "2025-03-31",
      "organization_id": "~{\"classification\": \"lower\"}",
      "classification": [],
      "related_entities": [],
      "_processing": {
        "log_file_created": "2025-10-25T03:23:16Z"
      }
    },
    {
      "description": "Senate substituted House Bill for companion Senate Bill.",
      "date": "2025-03-31",
      "organization_id": "~{\"classification\": \"lower\"}",
      "classification": [
        "substitution"
      ],
      "related_entities": [],
      "_processing": {
        "log_file_created": "2025-10-25T03:23:16Z"
      }
    },
    {
      "description": "H. Placed on Message Calendar 4/7/2025",
      "date": "2025-04-03",
      "organization_id": "~{\"classification\": \"lower\"}",
      "classification": [],
      "related_entities": [],
      "_processing": {
        "log_file_created": "2025-10-25T03:23:16Z"
      }
    },
    {
      "description": "H. concurred in S. am. no. 1 Ayes 73, Nays 22 PNV 0 HB1237",
      "date": "2025-04-07",
      "organization_id": "~{\"classification\": \"lower\"}",
      "classification": [],
      "related_entities": [],
      "_processing": {
        "log_file_created": "2025-10-25T03:23:16Z"
      }
    },
    {
      "description": "Enrolled; ready for sig. of H. Speaker.",
      "date": "2025-04-08",
      "organization_id": "~{\"classification\": \"lower\"}",
      "classification": [
        "enrolled"
      ],
      "related_entities": [],
      "_processing": {
        "log_file_created": "2025-10-25T03:23:16Z"
      }
    },
    {
      "description": "Signed by H. Speaker",
      "date": "2025-04-10",
      "organization_id": "~{\"classification\": \"lower\"}",
      "classification": [
        "passage"
      ],
      "related_entities": [],
      "_processing": {
        "log_file_created": "2025-10-25T03:23:16Z"
      }
    },
    {
      "description": "Signed by Senate Speaker",
      "date": "2025-04-14",
      "organization_id": "~{\"classification\": \"upper\"}",
      "classification": [
        "passage"
      ],
      "related_entities": [],
      "_processing": {
        "log_file_created": "2025-10-25T03:23:16Z"
      }
    },
    {
      "description": "Transmitted to Governor for his action.",
      "date": "2025-04-16",
      "organization_id": "~{\"classification\": \"lower\"}",
      "classification": [
        "executive-receipt"
      ],
      "related_entities": [],
      "_processing": {
        "log_file_created": "2025-10-25T03:23:16Z"
      }
    },
    {
      "description": "Signed by Governor.",
      "date": "2025-04-24",
      "organization_id": "~{\"classification\": \"lower\"}",
      "classification": [
        "executive-signature"
      ],
      "related_entities": [],
      "_processing": {
        "log_file_created": "2025-10-25T03:23:16Z"
      }
    },
    {
      "description": "Effective date(s) 04/24/2025",
      "date": "2025-04-28",
      "organization_id": "~{\"classification\": \"lower\"}",
      "classification": [],
      "related_entities": [],
      "_processing": {
        "log_file_created": "2025-10-25T03:23:16Z"
      }
    },
    {
      "description": "Pub. Ch. 294",
      "date": "2025-04-28",
      "organization_id": "~{\"classification\": \"lower\"}",
      "classification": [],
      "related_entities": [],
      "_processing": {
        "log_file_created": "2025-10-25T03:23:16Z"
      }
    }
  ],
  "sponsorships": [
    {
      "name": "Zachary",
      "classification": "primary",
      "entity_type": "person",
      "primary": true,
      "person_id": "~{\"name\": \"Zachary\"}",
      "organization_id": null
    }
  ],
  "related_bills": [
    {
      "identifier": "SB 1235",
      "legislative_session": "114",
      "relation_type": "companion"
    }
  ],
  "versions": [
    {
      "note": "Current Version",
      "links": [
        {
          "url": "https://www.capitol.tn.gov/Bills/114/Bill/HB1237.pdf",
          "media_type": "application/pdf"
        }
      ],
      "date": "",
      "classification": ""
    },
    {
      "note": "Amendment HA0053",
      "links": [
        {
          "url": "https://www.capitol.tn.gov/Bills/114/Amend/HA0053.pdf",
          "media_type": "application/pdf"
        }
      ],
      "date": "",
      "classification": ""
    },
    {
      "note": "Amendment SA0137",
      "links": [
        {
          "url": "https://www.capitol.tn.gov/Bills/114/Amend/SA0137.pdf",
          "media_type": "application/pdf"
        }
      ],
      "date": "",
      "classification": ""
    }
  ],
  "documents": [
    {
      "note": "Fiscal Note",
      "links": [
        {
          "url": "http://www.capitol.tn.gov/Bills/114/Fiscal/SB1235.pdf",
          "media_type": ""
        }
      ],
      "date": "",
      "classification": ""
    },
    {
      "note": "Fiscal Memo for HA0053 (4024)",
      "links": [
        {
          "url": "http://www.capitol.tn.gov/Bills/114/Fiscal/FM0280.pdf",
          "media_type": ""
        }
      ],
      "date": "",
      "classification": ""
    },
    {
      "note": "Fiscal Memo for SA0137 (5154)",
      "links": [
        {
          "url": "http://www.capitol.tn.gov/Bills/114/Fiscal/FM0601.pdf",
          "media_type": ""
        }
      ],
      "date": "",
      "classification": ""
    }
  ],
  "citations": [],
  "sources": [
    {
      "url": "http://wapp.capitol.tn.gov/apps/BillInfo/default.aspx?BillNumber=HB1237&GA=114",
      "note": ""
    }
  ],
  "extras": {},
  "jurisdiction": {
    "id": "ocd-jurisdiction/country:us/state:tn/government",
    "name": "Tennessee",
    "classification": "state",
    "division_id": "ocd-division/country:us/state:tn"
  },
  "_processing": {
    "logs_latest_update": "2025-10-25T03:23:16Z",
    "text_extraction_latest_update": "2025-10-25T11:23:49.531268Z"
  }
}