{
  "legislative_session": "114",
  "identifier": "HB 0153",
  "title": "Mobile Homes and Manufactured Buildings - As introduced, requires the department of transportation to submit a brief written summary to the committee of the house of representatives with jurisdiction over transportation matters and the transportation and safety committee of the senate no later than March 15, 2026, and March 15 of each subsequent year, concerning placards issued to transporters of manufactured homes pursuant to this section, including data on unsafe and erratic driving reported to the department using the telephone number that appears on the placards. - Amends TCA Title 55; Title 62; Title 67 and Title 68.",
  "from_organization": "~{\"classification\": \"lower\"}",
  "classification": [
    "bill"
  ],
  "subject": [
    "Mobile Homes and Manufactured Buildings"
  ],
  "abstracts": [],
  "other_titles": [],
  "other_identifiers": [
    {
      "identifier": "SB 0173"
    }
  ],
  "actions": [
    {
      "description": "Filed for introduction",
      "date": "2025-01-14",
      "organization_id": "~{\"classification\": \"lower\"}",
      "classification": [
        "filing"
      ],
      "related_entities": [],
      "_processing": {
        "log_file_created": "2025-10-25T03:23:11Z"
      }
    },
    {
      "description": "Intro., P1C.",
      "date": "2025-01-15",
      "organization_id": "~{\"classification\": \"lower\"}",
      "classification": [
        "introduction"
      ],
      "related_entities": [],
      "_processing": {
        "log_file_created": "2025-10-25T03:23:11Z"
      }
    },
    {
      "description": "Ref. to caption bill, held on desk - pending amdt.",
      "date": "2025-01-16",
      "organization_id": "~{\"classification\": \"lower\"}",
      "classification": [
        "referral-committee"
      ],
      "related_entities": [],
      "_processing": {
        "log_file_created": "2025-10-25T03:23:11Z"
      }
    },
    {
      "description": "P2C held on desk pending appointment of Standing Committees",
      "date": "2025-01-16",
      "organization_id": "~{\"classification\": \"lower\"}",
      "classification": [],
      "related_entities": [],
      "_processing": {
        "log_file_created": "2025-10-25T03:23:11Z"
      }
    }
  ],
  "sponsorships": [
    {
      "name": "Atchley",
      "classification": "primary",
      "entity_type": "person",
      "primary": true,
      "person_id": "~{\"name\": \"Atchley\"}",
      "organization_id": null
    }
  ],
  "related_bills": [
    {
      "identifier": "SB 173",
      "legislative_session": "114",
      "relation_type": "companion"
    }
  ],
  "versions": [
    {
      "note": "Current Version",
      "links": [
        {
          "url": "https://www.capitol.tn.gov/Bills/114/Bill/HB0153.pdf",
          "media_type": "application/pdf"
        }
      ],
      "date": "",
      "classification": ""
    }
  ],
  "documents": [
    {
      "note": "Fiscal Note",
      "links": [
        {
          "url": "http://www.capitol.tn.gov/Bills/114/Fiscal/HB0153.pdf",
          "media_type": ""
        }
      ],
      "date": "",
      "classification": ""
    }
  ],
  "citations": [],
  "sources": [
    {
      "url": "http://wapp.capitol.tn.gov/apps/BillInfo/default.aspx?BillNumber=HB0153&GA=114",
      "note": ""
    }
  ],
  "extras": {},
  "jurisdiction": {
    "id": "ocd-jurisdiction/country:us/state:tn/government",
    "name": "Tennessee",
    "classification": "state",
    "division_id": "ocd-division/country:us/state:tn"
  },
  "_processing": {
    "logs_latest_update": "2025-10-25T03:23:11Z"
  }
}