{
  "legislative_session": "114",
  "identifier": "SJR 0215",
  "title": "Memorials, Recognition - Osteoporosis Awareness and Prevention Month, May 2025 -",
  "from_organization": "~{\"classification\": \"upper\"}",
  "classification": [
    "joint resolution"
  ],
  "subject": [
    "Memorials",
    "Recognition"
  ],
  "abstracts": [],
  "other_titles": [],
  "other_identifiers": [],
  "actions": [
    {
      "description": "Filed for introduction",
      "date": "2025-03-05",
      "organization_id": "~{\"classification\": \"upper\"}",
      "classification": [
        "filing"
      ],
      "related_entities": [],
      "_processing": {
        "log_file_created": "2025-10-25T03:23:08Z"
      }
    },
    {
      "description": "Introduced, Passed on First Consideration",
      "date": "2025-03-06",
      "organization_id": "~{\"classification\": \"upper\"}",
      "classification": [
        "introduction"
      ],
      "related_entities": [],
      "_processing": {
        "log_file_created": "2025-10-25T03:23:08Z"
      }
    },
    {
      "description": "Passed on Second Consideration, refer to Senate Health & Welfare Committee",
      "date": "2025-03-10",
      "organization_id": "~{\"classification\": \"upper\"}",
      "classification": [
        "passage"
      ],
      "related_entities": [],
      "_processing": {
        "log_file_created": "2025-10-25T03:23:08Z"
      }
    },
    {
      "description": "Placed on Senate Health and Welfare Committee calendar for 3/19/2025",
      "date": "2025-03-12",
      "organization_id": "~{\"classification\": \"upper\"}",
      "classification": [],
      "related_entities": [],
      "_processing": {
        "log_file_created": "2025-10-25T03:23:08Z"
      }
    },
    {
      "description": "Assigned to General Subcommittee of Senate Health & Welfare Committee",
      "date": "2025-03-19",
      "organization_id": "~{\"classification\": \"upper\"}",
      "classification": [
        "referral-committee"
      ],
      "related_entities": [],
      "_processing": {
        "log_file_created": "2025-10-25T03:23:08Z"
      }
    }
  ],
  "sponsorships": [
    {
      "name": "Massey",
      "classification": "primary",
      "entity_type": "person",
      "primary": true,
      "person_id": "~{\"name\": \"Massey\"}",
      "organization_id": null
    }
  ],
  "related_bills": [],
  "versions": [
    {
      "note": "Current Version",
      "links": [
        {
          "url": "https://www.capitol.tn.gov/Bills/114/Bill/SJR0215.pdf",
          "media_type": "application/pdf"
        }
      ],
      "date": "",
      "classification": ""
    }
  ],
  "documents": [
    {
      "note": "Fiscal Note",
      "links": [
        {
          "url": "http://www.capitol.tn.gov/Bills/114/Fiscal/SJR0215.pdf",
          "media_type": ""
        }
      ],
      "date": "",
      "classification": ""
    }
  ],
  "citations": [],
  "sources": [
    {
      "url": "http://wapp.capitol.tn.gov/apps/BillInfo/default.aspx?BillNumber=SJR0215&GA=114",
      "note": ""
    }
  ],
  "extras": {},
  "jurisdiction": {
    "id": "ocd-jurisdiction/country:us/state:tn/government",
    "name": "Tennessee",
    "classification": "state",
    "division_id": "ocd-division/country:us/state:tn"
  },
  "_processing": {
    "logs_latest_update": "2025-10-25T03:23:08Z",
    "text_extraction_latest_update": "2025-10-25T09:28:40.447895Z"
  }
}