{
  "legislative_session": "114",
  "identifier": "HJR 0293",
  "title": "Memorials, Recognition - T.B. Sutton General Store, 100th anniversary -",
  "from_organization": "~{\"classification\": \"lower\"}",
  "classification": [
    "joint resolution"
  ],
  "subject": [
    "Memorials",
    "Recognition"
  ],
  "abstracts": [],
  "other_titles": [],
  "other_identifiers": [],
  "actions": [
    {
      "description": "Filed for introduction",
      "date": "2025-02-26",
      "organization_id": "~{\"classification\": \"lower\"}",
      "classification": [
        "filing"
      ],
      "related_entities": [],
      "_processing": {
        "log_file_created": "2025-10-25T03:23:16Z"
      }
    },
    {
      "description": "Withdrawn.",
      "date": "2025-02-27",
      "organization_id": "~{\"classification\": \"lower\"}",
      "classification": [
        "withdrawal"
      ],
      "related_entities": [],
      "_processing": {
        "log_file_created": "2025-10-25T03:23:16Z"
      }
    },
    {
      "description": "Intro., placed on H. consent cal. 3/3/2025",
      "date": "2025-02-27",
      "organization_id": "~{\"classification\": \"lower\"}",
      "classification": [
        "introduction"
      ],
      "related_entities": [],
      "_processing": {
        "log_file_created": "2025-10-25T03:23:16Z"
      }
    }
  ],
  "sponsorships": [
    {
      "name": "Hale",
      "classification": "primary",
      "entity_type": "person",
      "primary": true,
      "person_id": "~{\"name\": \"Hale\"}",
      "organization_id": null
    }
  ],
  "related_bills": [],
  "versions": [
    {
      "note": "Current Version",
      "links": [
        {
          "url": "https://www.capitol.tn.gov/Bills/114/Bill/HJR0293.pdf",
          "media_type": "application/pdf"
        }
      ],
      "date": "",
      "classification": ""
    }
  ],
  "documents": [],
  "citations": [],
  "sources": [
    {
      "url": "http://wapp.capitol.tn.gov/apps/BillInfo/default.aspx?BillNumber=HJR0293&GA=114",
      "note": ""
    }
  ],
  "extras": {},
  "jurisdiction": {
    "id": "ocd-jurisdiction/country:us/state:tn/government",
    "name": "Tennessee",
    "classification": "state",
    "division_id": "ocd-division/country:us/state:tn"
  },
  "_processing": {
    "logs_latest_update": "2025-10-25T03:23:16Z"
  }
}