{
  "legislative_session": "114",
  "identifier": "SB 0046",
  "title": "Celina - Subject to local approval, increases the number of aldermen from three to five. - Amends Chapter 90 of the Private Acts of 1991; as amended.",
  "from_organization": "~{\"classification\": \"upper\"}",
  "classification": [
    "bill"
  ],
  "subject": [
    "Celina"
  ],
  "abstracts": [],
  "other_titles": [],
  "other_identifiers": [
    {
      "identifier": "HB 0050"
    }
  ],
  "actions": [
    {
      "description": "Filed for introduction",
      "date": "2025-01-08",
      "organization_id": "~{\"classification\": \"upper\"}",
      "classification": [
        "filing"
      ],
      "related_entities": [],
      "_processing": {
        "log_file_created": "2025-10-25T03:23:08Z"
      }
    },
    {
      "description": "Introduced, Passed on First Consideration",
      "date": "2025-01-14",
      "organization_id": "~{\"classification\": \"upper\"}",
      "classification": [
        "introduction"
      ],
      "related_entities": [],
      "_processing": {
        "log_file_created": "2025-10-25T03:23:08Z"
      }
    },
    {
      "description": "Placed on Senate Local Consent Calendar  for 1/16/2025",
      "date": "2025-01-15",
      "organization_id": "~{\"classification\": \"upper\"}",
      "classification": [],
      "related_entities": [],
      "_processing": {
        "log_file_created": "2025-10-25T03:23:08Z"
      }
    },
    {
      "description": "Passed on Second Consideration, held on desk. Local Bill",
      "date": "2025-01-15",
      "organization_id": "~{\"classification\": \"upper\"}",
      "classification": [
        "passage"
      ],
      "related_entities": [],
      "_processing": {
        "log_file_created": "2025-10-25T03:23:08Z"
      }
    },
    {
      "description": "Engrossed; ready for transmission to House",
      "date": "2025-01-16",
      "organization_id": "~{\"classification\": \"upper\"}",
      "classification": [
        "receipt"
      ],
      "related_entities": [],
      "_processing": {
        "log_file_created": "2025-10-25T03:23:08Z"
      }
    },
    {
      "description": "Passed Senate, Ayes 33, Nays 0",
      "date": "2025-01-16",
      "organization_id": "~{\"classification\": \"upper\"}",
      "classification": [
        "passage"
      ],
      "related_entities": [],
      "_processing": {
        "log_file_created": "2025-10-25T03:23:08Z"
      }
    },
    {
      "description": "Rcvd. from S., held on H. desk.",
      "date": "2025-01-27",
      "organization_id": "~{\"classification\": \"upper\"}",
      "classification": [],
      "related_entities": [],
      "_processing": {
        "log_file_created": "2025-10-25T03:23:08Z"
      }
    },
    {
      "description": "Passed H., Ayes 90, Nays 0, PNV 0",
      "date": "2025-03-03",
      "organization_id": "~{\"classification\": \"lower\"}",
      "classification": [
        "passage"
      ],
      "related_entities": [],
      "_processing": {
        "log_file_created": "2025-10-25T03:23:08Z"
      }
    },
    {
      "description": "Subst. for comp. HB.",
      "date": "2025-03-03",
      "organization_id": "~{\"classification\": \"upper\"}",
      "classification": [
        "substitution"
      ],
      "related_entities": [],
      "_processing": {
        "log_file_created": "2025-10-25T03:23:08Z"
      }
    },
    {
      "description": "Enrolled and ready for signatures",
      "date": "2025-03-04",
      "organization_id": "~{\"classification\": \"upper\"}",
      "classification": [
        "enrolled"
      ],
      "related_entities": [],
      "_processing": {
        "log_file_created": "2025-10-25T03:23:08Z"
      }
    },
    {
      "description": "Signed by Senate Speaker",
      "date": "2025-03-05",
      "organization_id": "~{\"classification\": \"upper\"}",
      "classification": [
        "passage"
      ],
      "related_entities": [],
      "_processing": {
        "log_file_created": "2025-10-25T03:23:08Z"
      }
    },
    {
      "description": "Signed by H. Speaker",
      "date": "2025-03-06",
      "organization_id": "~{\"classification\": \"lower\"}",
      "classification": [
        "passage"
      ],
      "related_entities": [],
      "_processing": {
        "log_file_created": "2025-10-25T03:23:08Z"
      }
    },
    {
      "description": "Transmitted to Governor for action.",
      "date": "2025-03-10",
      "organization_id": "~{\"classification\": \"upper\"}",
      "classification": [
        "executive-receipt"
      ],
      "related_entities": [],
      "_processing": {
        "log_file_created": "2025-10-25T03:23:08Z"
      }
    },
    {
      "description": "Signed by Governor.",
      "date": "2025-03-12",
      "organization_id": "~{\"classification\": \"upper\"}",
      "classification": [
        "executive-signature"
      ],
      "related_entities": [],
      "_processing": {
        "log_file_created": "2025-10-25T03:23:08Z"
      }
    },
    {
      "description": "Pr. Ch. 1",
      "date": "2025-03-21",
      "organization_id": "~{\"classification\": \"upper\"}",
      "classification": [],
      "related_entities": [],
      "_processing": {
        "log_file_created": "2025-10-25T03:23:08Z"
      }
    }
  ],
  "sponsorships": [
    {
      "name": "Yager",
      "classification": "primary",
      "entity_type": "person",
      "primary": true,
      "person_id": "~{\"name\": \"Yager\"}",
      "organization_id": null
    }
  ],
  "related_bills": [
    {
      "identifier": "HB 50",
      "legislative_session": "114",
      "relation_type": "companion"
    }
  ],
  "versions": [
    {
      "note": "Current Version",
      "links": [
        {
          "url": "https://www.capitol.tn.gov/Bills/114/Bill/SB0046.pdf",
          "media_type": "application/pdf"
        }
      ],
      "date": "",
      "classification": ""
    }
  ],
  "documents": [],
  "citations": [],
  "sources": [
    {
      "url": "http://wapp.capitol.tn.gov/apps/BillInfo/default.aspx?BillNumber=SB0046&GA=114",
      "note": ""
    }
  ],
  "extras": {},
  "jurisdiction": {
    "id": "ocd-jurisdiction/country:us/state:tn/government",
    "name": "Tennessee",
    "classification": "state",
    "division_id": "ocd-division/country:us/state:tn"
  },
  "_processing": {
    "logs_latest_update": "2025-10-25T03:23:08Z"
  }
}