{
  "legislative_session": "114",
  "identifier": "HB 0754",
  "title": "Health Care - As introduced, requires gender clinics accepting funds from this state to perform gender transition procedures to also perform detransition procedures; requires insurance entities providing coverage of gender transition procedures to also cover detransition procedures; requires certain gender clinics and insurance entities to report information regarding detransition procedures to the department of health. - Amends TCA Title 1; Title 4; Title 33; Title 56; Title 63; Title 68 and Title 71.",
  "from_organization": "~{\"classification\": \"lower\"}",
  "classification": [
    "bill"
  ],
  "subject": [
    "Health Care"
  ],
  "abstracts": [],
  "other_titles": [],
  "other_identifiers": [
    {
      "identifier": "SB 0676"
    }
  ],
  "actions": [
    {
      "description": "Filed for introduction",
      "date": "2025-02-03",
      "organization_id": "~{\"classification\": \"lower\"}",
      "classification": [
        "filing"
      ],
      "related_entities": [],
      "_processing": {
        "log_file_created": "2025-10-25T03:23:19Z"
      }
    },
    {
      "description": "Intro., P1C.",
      "date": "2025-02-05",
      "organization_id": "~{\"classification\": \"lower\"}",
      "classification": [
        "introduction"
      ],
      "related_entities": [],
      "_processing": {
        "log_file_created": "2025-10-25T03:23:19Z"
      }
    },
    {
      "description": "P2C, ref. to Health Committee",
      "date": "2025-02-06",
      "organization_id": "~{\"classification\": \"lower\"}",
      "classification": [
        "referral-committee"
      ],
      "related_entities": [],
      "_processing": {
        "log_file_created": "2025-10-25T03:23:19Z"
      }
    },
    {
      "description": "Assigned to s/c Population Health Subcommittee",
      "date": "2025-02-10",
      "organization_id": "~{\"classification\": \"lower\"}",
      "classification": [
        "referral-committee"
      ],
      "related_entities": [],
      "_processing": {
        "log_file_created": "2025-10-25T03:23:19Z"
      }
    },
    {
      "description": "Placed on s/c cal Population Health Subcommittee for 3/11/2025",
      "date": "2025-03-05",
      "organization_id": "~{\"classification\": \"lower\"}",
      "classification": [],
      "related_entities": [],
      "_processing": {
        "log_file_created": "2025-10-25T03:23:19Z"
      }
    },
    {
      "description": "Rec for pass if am by s/c ref. to  Health Committee",
      "date": "2025-03-11",
      "organization_id": "~{\"classification\": \"lower\"}",
      "classification": [
        "referral-committee"
      ],
      "related_entities": [],
      "_processing": {
        "log_file_created": "2025-10-25T03:23:19Z"
      }
    },
    {
      "description": "Placed on cal. Health Committee for 3/18/2025",
      "date": "2025-03-12",
      "organization_id": "~{\"classification\": \"lower\"}",
      "classification": [],
      "related_entities": [],
      "_processing": {
        "log_file_created": "2025-10-25T03:23:19Z"
      }
    },
    {
      "description": "Assigned to s/c Finance, Ways, and Means Subcommittee",
      "date": "2025-03-18",
      "organization_id": "~{\"classification\": \"lower\"}",
      "classification": [
        "referral-committee"
      ],
      "related_entities": [],
      "_processing": {
        "log_file_created": "2025-10-25T03:23:19Z"
      }
    },
    {
      "description": "Rec. for pass. if am., ref. to  Finance, Ways, and Means Committee",
      "date": "2025-03-18",
      "organization_id": "~{\"classification\": \"lower\"}",
      "classification": [
        "committee-passage-favorable"
      ],
      "related_entities": [],
      "_processing": {
        "log_file_created": "2025-10-25T03:23:19Z"
      }
    },
    {
      "description": "Placed on s/c cal Finance, Ways, and Means Subcommittee for 3/26/2025",
      "date": "2025-03-19",
      "organization_id": "~{\"classification\": \"lower\"}",
      "classification": [],
      "related_entities": [],
      "_processing": {
        "log_file_created": "2025-10-25T03:23:19Z"
      }
    },
    {
      "description": "Placed behind the budget",
      "date": "2025-03-26",
      "organization_id": "~{\"classification\": \"lower\"}",
      "classification": [],
      "related_entities": [],
      "_processing": {
        "log_file_created": "2025-10-25T03:23:19Z"
      }
    },
    {
      "description": "Placed on s/c cal Finance, Ways, and Means Subcommittee for 4/14/2025",
      "date": "2025-04-09",
      "organization_id": "~{\"classification\": \"lower\"}",
      "classification": [],
      "related_entities": [],
      "_processing": {
        "log_file_created": "2025-10-25T03:23:19Z"
      }
    }
  ],
  "sponsorships": [
    {
      "name": "Faison",
      "classification": "primary",
      "entity_type": "person",
      "primary": true,
      "person_id": "~{\"name\": \"Faison\"}",
      "organization_id": null
    }
  ],
  "related_bills": [
    {
      "identifier": "SB 676",
      "legislative_session": "114",
      "relation_type": "companion"
    }
  ],
  "versions": [
    {
      "note": "Current Version",
      "links": [
        {
          "url": "https://www.capitol.tn.gov/Bills/114/Bill/HB0754.pdf",
          "media_type": "application/pdf"
        }
      ],
      "date": "",
      "classification": ""
    },
    {
      "note": "Amendment HA0111",
      "links": [
        {
          "url": "https://www.capitol.tn.gov/Bills/114/Amend/HA0111.pdf",
          "media_type": "application/pdf"
        }
      ],
      "date": "",
      "classification": ""
    },
    {
      "note": "Amendment SA0242",
      "links": [
        {
          "url": "https://www.capitol.tn.gov/Bills/114/Amend/SA0242.pdf",
          "media_type": "application/pdf"
        }
      ],
      "date": "",
      "classification": ""
    }
  ],
  "documents": [
    {
      "note": "Fiscal Note",
      "links": [
        {
          "url": "http://www.capitol.tn.gov/Bills/114/Fiscal/SB0676.pdf",
          "media_type": ""
        }
      ],
      "date": "",
      "classification": ""
    },
    {
      "note": "Fiscal Memo for HA0111 (5099)",
      "links": [
        {
          "url": "http://www.capitol.tn.gov/Bills/114/Fiscal/FM0529.pdf",
          "media_type": ""
        }
      ],
      "date": "",
      "classification": ""
    }
  ],
  "citations": [],
  "sources": [
    {
      "url": "http://wapp.capitol.tn.gov/apps/BillInfo/default.aspx?BillNumber=HB0754&GA=114",
      "note": ""
    }
  ],
  "extras": {},
  "jurisdiction": {
    "id": "ocd-jurisdiction/country:us/state:tn/government",
    "name": "Tennessee",
    "classification": "state",
    "division_id": "ocd-division/country:us/state:tn"
  },
  "_processing": {
    "logs_latest_update": "2025-10-25T03:23:19Z"
  }
}